teamtime/__init__.py
teamtime/team_member.py
teamtime/teamtime.py
teamtime-2.0.0.post1.dist-info/entry_points.txt
teamtime-2.0.0.post1.dist-info/WHEEL
teamtime-2.0.0.post1.dist-info/METADATA
teamtime-2.0.0.post1.dist-info/RECORD
