Metadata-Version: 2.1
Name: teamtime
Version: 2.0.0.post1
Summary: A tool for keeping track of staff in multiple timezones
Home-page: https://github.com/mssalvatore/teamTime
License: GPLv3
Author: Joe McManus
Author-email: josephmc@alumni.cmu.edu
Requires-Python: >=3.8,<4.0
Classifier: Development Status :: 5 - Production/Stable
Classifier: License :: OSI Approved :: GNU General Public License v3 (GPLv3)
Classifier: License :: Other/Proprietary License
Classifier: Operating System :: OS Independent
Classifier: Programming Language :: Python :: 3
Classifier: Programming Language :: Python :: 3.10
Classifier: Programming Language :: Python :: 3.8
Classifier: Programming Language :: Python :: 3.9
Classifier: Topic :: Office/Business :: Scheduling
Classifier: Topic :: Utilities
Requires-Dist: geopy (>=2.3.0,<3.0.0)
Requires-Dist: pandas (>=1.5.2,<2.0.0)
Requires-Dist: plotly (>=5.11.0,<6.0.0)
Requires-Dist: prettytable (>=3.5.0,<4.0.0)
Requires-Dist: pytz (>=2022.6,<2023.0)
Project-URL: Repository, https://github.com/mssalvatore/teamTime
